{"otherData": {},"traceEvents":[{"cat":"function","dur":2297,"name":"void __cdecl ETOD::Renderer2D::Shutdown(void)","ph":"X","pid":0,"tid":1604011008,"ts":21268108114},{"cat":"function","dur":2881,"name":"__cdecl ETOD::Application::~Application(void)","ph":"X","pid":0,"tid":1604011008,"ts":21268108112},{"cat":"function","dur":1,"name":"void __cdecl ETOD::EditorLayer::OnDetach(void)","ph":"X","pid":0,"tid":1604011008,"ts":21268111511},{"cat":"function","dur":51,"name":"__cdecl ETOD::OpenGLTexture2D::~OpenGLTexture2D(void)","ph":"X","pid":0,"tid":1604011008,"ts":21268111977},{"cat":"function","dur":29,"name":"__cdecl ETOD::OpenGLTexture2D::~OpenGLTexture2D(void)","ph":"X","pid":0,"tid":1604011008,"ts":21268112373},{"cat":"function","dur":76,"name":"__cdecl ETOD::OpenGLTexture2D::~OpenGLTexture2D(void)","ph":"X","pid":0,"tid":1604011008,"ts":21268112727},{"cat":"function","dur":29,"name":"__cdecl ETOD::OpenGLTexture2D::~OpenGLTexture2D(void)","ph":"X","pid":0,"tid":1604011008,"ts":21268113135},{"cat":"function","dur":31,"name":"__cdecl ETOD::OpenGLTexture2D::~OpenGLTexture2D(void)","ph":"X","pid":0,"tid":1604011008,"ts":21268113492},{"cat":"function","dur":85,"name":"__cdecl ETOD::OpenGLTexture2D::~OpenGLTexture2D(void)","ph":"X","pid":0,"tid":1604011008,"ts":21268114161},{"cat":"function","dur":21140,"name":"void __cdecl ETOD::ImGuiLayer::OnDetach(void)","ph":"X","pid":0,"tid":1604011008,"ts":21268116098},{"cat":"function","dur":164105,"name":"void __cdecl ETOD::WindowsWindow::Shutdown(void)","ph":"X","pid":0,"tid":1604011008,"ts":21268137662},{"cat":"function","dur":164341,"name":"__cdecl ETOD::WindowsWindow::~WindowsWindow(void)","ph":"X","pid":0,"tid":1604011008,"ts":21268137662}]}