{"otherData": {},"traceEvents":[{"cat":"function","dur":126412,"name":"glfwInit","ph":"X","pid":0,"tid":434582969,"ts":178292086},{"cat":"function","dur":232083,"name":"glfwCreateWindow","ph":"X","pid":0,"tid":434582969,"ts":178418715},{"cat":"function","dur":2894,"name":"void __cdecl ETOD::OpenGLContext::Init(void)","ph":"X","pid":0,"tid":434582969,"ts":178650942},{"cat":"function","dur":16,"name":"void __cdecl ETOD::WindowsWindow::SetVSync(bool)","ph":"X","pid":0,"tid":434582969,"ts":178653943},{"cat":"function","dur":362391,"name":"void __cdecl ETOD::WindowsWindow::Init(const struct ETOD::WindowProps &)","ph":"X","pid":0,"tid":434582969,"ts":178291656},{"cat":"function","dur":362463,"name":"__cdecl ETOD::WindowsWindow::WindowsWindow(const struct ETOD::WindowProps &)","ph":"X","pid":0,"tid":434582969,"ts":178291654},{"cat":"function","dur":15,"name":"void __cdecl ETOD::OpenGLRendererAPI::Init(void)","ph":"X","pid":0,"tid":434582969,"ts":178654211},{"cat":"function","dur":57,"name":"__cdecl ETOD::OpenGLVertexArray::OpenGLVertexArray(void)","ph":"X","pid":0,"tid":434582969,"ts":178654313},{"cat":"function","dur":84,"name":"__cdecl ETOD::OpenGLVertexBuffer::OpenGLVertexBuffer(unsigned int)","ph":"X","pid":0,"tid":434582969,"ts":178654460},{"cat":"function","dur":1,"name":"void __cdecl ETOD::OpenGLVertexBuffer::Bind(void) const","ph":"X","pid":0,"tid":434582969,"ts":178654668},{"cat":"function","dur":94,"name":"void __cdecl ETOD::OpenGLVertexArray::AddVertexBuffer(const class std::shared_ptr<class ETOD::VertexBuffer> &)","ph":"X","pid":0,"tid":434582969,"ts":178654663},{"cat":"function","dur":1003,"name":"__cdecl ETOD::OpenGLIndexBuffer::OpenGLIndexBuffer(unsigned int *,unsigned int)","ph":"X","pid":0,"tid":434582969,"ts":178656240},{"cat":"function","dur":1,"name":"void __cdecl ETOD::OpenGLIndexBuffer::Bind(void) const","ph":"X","pid":0,"tid":434582969,"ts":178657383},{"cat":"function","dur":64,"name":"void __cdecl ETOD::OpenGLVertexArray::SetIndexBuffer(const class std::shared_ptr<class ETOD::IndexBuffer> &)","ph":"X","pid":0,"tid":434582969,"ts":178657380},{"cat":"function","dur":1514,"name":"__cdecl ETOD::OpenGLTexture2D::OpenGLTexture2D(unsigned int,unsigned int)","ph":"X","pid":0,"tid":434582969,"ts":178657525},{"cat":"function","dur":1003,"name":"void __cdecl ETOD::OpenGLTexture2D::SetData(void *,unsigned int)","ph":"X","pid":0,"tid":434582969,"ts":178659552},{"cat":"function","dur":251,"name":"class std::basic_string<char,struct std::char_traits<char>,class std::allocator<char> > __cdecl ETOD::OpenGLShader::ReadFile(const class std::basic_string<char,struct std::char_traits<char>,class std::allocator<char> > &)","ph":"X","pid":0,"tid":434582969,"ts":178660939},{"cat":"function","dur":143,"name":"class std::unordered_map<unsigned int,class std::basic_string<char,struct std::char_traits<char>,class std::allocator<char> >,struct std::hash<unsigned int>,struct std::equal_to<unsigned int>,class std::allocator<struct std::pair<unsigned int const ,class std::basic_string<char,struct std::char_traits<char>,class std::allocator<char> > > > > __cdecl ETOD::OpenGLShader::PreProcess(const class std::basic_string<char,struct std::char_traits<char>,class std::allocator<char> > &)","ph":"X","pid":0,"tid":434582969,"ts":178661265},{"cat":"function","dur":82656,"name":"__cdecl ETOD::OpenGLShader::OpenGLShader(const class std::basic_string<char,struct std::char_traits<char>,class std::allocator<char> > &)","ph":"X","pid":0,"tid":434582969,"ts":178660851},{"cat":"function","dur":89358,"name":"void __cdecl ETOD::Renderer2D::Init(void)","ph":"X","pid":0,"tid":434582969,"ts":178654296},{"cat":"function","dur":89496,"name":"void __cdecl ETOD::Renderer::Init(void)","ph":"X","pid":0,"tid":434582969,"ts":178654204},{"cat":"function","dur":12221,"name":"void __cdecl ETOD::ImGuiLayer::OnAttach(void)","ph":"X","pid":0,"tid":434582969,"ts":178743767},{"cat":"function","dur":12309,"name":"void __cdecl ETOD::Application::PushOverlay(class ETOD::Layer *)","ph":"X","pid":0,"tid":434582969,"ts":178743757},{"cat":"function","dur":464468,"name":"__cdecl ETOD::Application::Application(const class std::basic_string<char,struct std::char_traits<char>,class std::allocator<char> > &,struct ETOD::ApplicationCommandLineArgs)","ph":"X","pid":0,"tid":434582969,"ts":178291633},{"cat":"function","dur":8,"name":"__cdecl ETOD::OrthographicCamera::OrthographicCamera(float,float,float,float)","ph":"X","pid":0,"tid":434582969,"ts":178756223},{"cat":"function","dur":8212,"name":"stbi_load - OpenGLTexture2D::OpenGLTexture2D(const std::string&)","ph":"X","pid":0,"tid":434582969,"ts":178756299},{"cat":"function","dur":19682,"name":"__cdecl ETOD::OpenGLTexture2D::OpenGLTexture2D(const class std::basic_string<char,struct std::char_traits<char>,class std::allocator<char> > &)","ph":"X","pid":0,"tid":434582969,"ts":178756293},{"cat":"function","dur":16612,"name":"stbi_load - OpenGLTexture2D::OpenGLTexture2D(const std::string&)","ph":"X","pid":0,"tid":434582969,"ts":178776130},{"cat":"function","dur":22025,"name":"__cdecl ETOD::OpenGLTexture2D::OpenGLTexture2D(const class std::basic_string<char,struct std::char_traits<char>,class std::allocator<char> > &)","ph":"X","pid":0,"tid":434582969,"ts":178776130},{"cat":"function","dur":259,"name":"stbi_load - OpenGLTexture2D::OpenGLTexture2D(const std::string&)","ph":"X","pid":0,"tid":434582969,"ts":178798341},{"cat":"function","dur":530,"name":"__cdecl ETOD::OpenGLTexture2D::OpenGLTexture2D(const class std::basic_string<char,struct std::char_traits<char>,class std::allocator<char> > &)","ph":"X","pid":0,"tid":434582969,"ts":178798341},{"cat":"function","dur":166,"name":"stbi_load - OpenGLTexture2D::OpenGLTexture2D(const std::string&)","ph":"X","pid":0,"tid":434582969,"ts":178798929},{"cat":"function","dur":351,"name":"__cdecl ETOD::OpenGLTexture2D::OpenGLTexture2D(const class std::basic_string<char,struct std::char_traits<char>,class std::allocator<char> > &)","ph":"X","pid":0,"tid":434582969,"ts":178798928},{"cat":"function","dur":133,"name":"stbi_load - OpenGLTexture2D::OpenGLTexture2D(const std::string&)","ph":"X","pid":0,"tid":434582969,"ts":178799332},{"cat":"function","dur":364,"name":"__cdecl ETOD::OpenGLTexture2D::OpenGLTexture2D(const class std::basic_string<char,struct std::char_traits<char>,class std::allocator<char> > &)","ph":"X","pid":0,"tid":434582969,"ts":178799332},{"cat":"function","dur":31154,"name":"void __cdecl ETOD::EditorLayer::OnAttach(void)","ph":"X","pid":0,"tid":434582969,"ts":178798332},{"cat":"function","dur":31286,"name":"void __cdecl ETOD::Application::PushLayer(class ETOD::Layer *)","ph":"X","pid":0,"tid":434582969,"ts":178798317}]}