{"otherData": {},"traceEvents":[{"cat":"function","dur":125837,"name":"glfwInit","ph":"X","pid":0,"tid":473454631,"ts":4232914501},{"cat":"function","dur":181638,"name":"glfwCreateWindow","ph":"X","pid":0,"tid":473454631,"ts":4233040654},{"cat":"function","dur":2335,"name":"void __cdecl ETOD::OpenGLContext::Init(void)","ph":"X","pid":0,"tid":473454631,"ts":4233222462},{"cat":"function","dur":17,"name":"void __cdecl ETOD::WindowsWindow::SetVSync(bool)","ph":"X","pid":0,"tid":473454631,"ts":4233224938},{"cat":"function","dur":311341,"name":"void __cdecl ETOD::WindowsWindow::Init(const struct ETOD::WindowProps &)","ph":"X","pid":0,"tid":473454631,"ts":4232913727},{"cat":"function","dur":311425,"name":"__cdecl ETOD::WindowsWindow::WindowsWindow(const struct ETOD::WindowProps &)","ph":"X","pid":0,"tid":473454631,"ts":4232913727},{"cat":"function","dur":24,"name":"void __cdecl ETOD::OpenGLRendererAPI::Init(void)","ph":"X","pid":0,"tid":473454631,"ts":4233225249},{"cat":"function","dur":22,"name":"__cdecl ETOD::OpenGLVertexArray::OpenGLVertexArray(void)","ph":"X","pid":0,"tid":473454631,"ts":4233225379},{"cat":"function","dur":262,"name":"__cdecl ETOD::OpenGLVertexBuffer::OpenGLVertexBuffer(unsigned int)","ph":"X","pid":0,"tid":473454631,"ts":4233225556},{"cat":"function","dur":1,"name":"void __cdecl ETOD::OpenGLVertexBuffer::Bind(void) const","ph":"X","pid":0,"tid":473454631,"ts":4233226010},{"cat":"function","dur":93,"name":"void __cdecl ETOD::OpenGLVertexArray::AddVertexBuffer(const class std::shared_ptr<class ETOD::VertexBuffer> &)","ph":"X","pid":0,"tid":473454631,"ts":4233226002},{"cat":"function","dur":1198,"name":"__cdecl ETOD::OpenGLIndexBuffer::OpenGLIndexBuffer(unsigned int *,unsigned int)","ph":"X","pid":0,"tid":473454631,"ts":4233227579},{"cat":"function","dur":0,"name":"void __cdecl ETOD::OpenGLIndexBuffer::Bind(void) const","ph":"X","pid":0,"tid":473454631,"ts":4233228879},{"cat":"function","dur":61,"name":"void __cdecl ETOD::OpenGLVertexArray::SetIndexBuffer(const class std::shared_ptr<class ETOD::IndexBuffer> &)","ph":"X","pid":0,"tid":473454631,"ts":4233228876},{"cat":"function","dur":1228,"name":"__cdecl ETOD::OpenGLTexture2D::OpenGLTexture2D(unsigned int,unsigned int)","ph":"X","pid":0,"tid":473454631,"ts":4233229011},{"cat":"function","dur":115,"name":"void __cdecl ETOD::OpenGLTexture2D::SetData(void *,unsigned int)","ph":"X","pid":0,"tid":473454631,"ts":4233230430},{"cat":"function","dur":348,"name":"class std::basic_string<char,struct std::char_traits<char>,class std::allocator<char> > __cdecl ETOD::OpenGLShader::ReadFile(const class std::basic_string<char,struct std::char_traits<char>,class std::allocator<char> > &)","ph":"X","pid":0,"tid":473454631,"ts":4233230728},{"cat":"function","dur":92,"name":"class std::unordered_map<unsigned int,class std::basic_string<char,struct std::char_traits<char>,class std::allocator<char> >,struct std::hash<unsigned int>,struct std::equal_to<unsigned int>,class std::allocator<struct std::pair<unsigned int const ,class std::basic_string<char,struct std::char_traits<char>,class std::allocator<char> > > > > __cdecl ETOD::OpenGLShader::PreProcess(const class std::basic_string<char,struct std::char_traits<char>,class std::allocator<char> > &)","ph":"X","pid":0,"tid":473454631,"ts":4233231147},{"cat":"function","dur":20667,"name":"void __cdecl ETOD::OpenGLShader::Compile(const class std::unordered_map<unsigned int,class std::basic_string<char,struct std::char_traits<char>,class std::allocator<char> >,struct std::hash<unsigned int>,struct std::equal_to<unsigned int>,class std::allocator<struct std::pair<unsigned int const ,class std::basic_string<char,struct std::char_traits<char>,class std::allocator<char> > > > > &)","ph":"X","pid":0,"tid":473454631,"ts":4233231316},{"cat":"function","dur":21389,"name":"__cdecl ETOD::OpenGLShader::OpenGLShader(const class std::basic_string<char,struct std::char_traits<char>,class std::allocator<char> > &)","ph":"X","pid":0,"tid":473454631,"ts":4233230721},{"cat":"function","dur":29,"name":"void __cdecl ETOD::OpenGLShader::Bind(void) const","ph":"X","pid":0,"tid":473454631,"ts":4233252170},{"cat":"function","dur":26989,"name":"void __cdecl ETOD::Renderer2D::Init(void)","ph":"X","pid":0,"tid":473454631,"ts":4233225327},{"cat":"function","dur":27117,"name":"void __cdecl ETOD::Renderer::Init(void)","ph":"X","pid":0,"tid":473454631,"ts":4233225244},{"cat":"function","dur":316,"name":"void __cdecl ETOD::ImGuiLayer::OnAttach(void)","ph":"X","pid":0,"tid":473454631,"ts":4233252410},{"cat":"function","dur":375,"name":"void __cdecl ETOD::Application::PushOverlay(class ETOD::Layer *)","ph":"X","pid":0,"tid":473454631,"ts":4233252401},{"cat":"function","dur":339135,"name":"__cdecl ETOD::Application::Application(const class std::basic_string<char,struct std::char_traits<char>,class std::allocator<char> > &)","ph":"X","pid":0,"tid":473454631,"ts":4232913702},{"cat":"function","dur":4,"name":"__cdecl ETOD::OrthographicCamera::OrthographicCamera(float,float,float,float)","ph":"X","pid":0,"tid":473454631,"ts":4233252910},{"cat":"function","dur":290,"name":"stbi_load - OpenGLTexture2D::OpenGLTexture2D(const std::string&)","ph":"X","pid":0,"tid":473454631,"ts":4233252970},{"cat":"function","dur":5801,"name":"__cdecl ETOD::OpenGLTexture2D::OpenGLTexture2D(const class std::basic_string<char,struct std::char_traits<char>,class std::allocator<char> > &)","ph":"X","pid":0,"tid":473454631,"ts":4233252970},{"cat":"function","dur":20373,"name":"void __cdecl ETOD::EditorLayer::OnAttach(void)","ph":"X","pid":0,"tid":473454631,"ts":4233252965},{"cat":"function","dur":20455,"name":"void __cdecl ETOD::Application::PushLayer(class ETOD::Layer *)","ph":"X","pid":0,"tid":473454631,"ts":4233252955}]}