{"otherData": {},"traceEvents":[{"cat":"function","dur":0,"name":"__cdecl ETOD::Application::~Application(void)","ph":"X","pid":0,"tid":3481124563,"ts":6134422353},{"cat":"function","dur":31,"name":"__cdecl ETOD::OpenGLTexture2D::~OpenGLTexture2D(void)","ph":"X","pid":0,"tid":3481124563,"ts":6134422432},{"cat":"function","dur":12657,"name":"void __cdecl ETOD::WindowsWindow::Shutdown(void)","ph":"X","pid":0,"tid":3481124563,"ts":6134422577},{"cat":"function","dur":12867,"name":"__cdecl ETOD::WindowsWindow::~WindowsWindow(void)","ph":"X","pid":0,"tid":3481124563,"ts":6134422577}]}