{"otherData": {},"traceEvents":[{"cat":"function","dur":109731,"name":"glfwInit","ph":"X","pid":0,"tid":434243838,"ts":20602179114},{"cat":"function","dur":136225,"name":"glfwCreateWindow","ph":"X","pid":0,"tid":434243838,"ts":20602289066},{"cat":"function","dur":3269,"name":"void __cdecl ETOD::OpenGLContext::Init(void)","ph":"X","pid":0,"tid":434243838,"ts":20602425467},{"cat":"function","dur":14,"name":"void __cdecl ETOD::WindowsWindow::SetVSync(bool)","ph":"X","pid":0,"tid":434243838,"ts":20602428823},{"cat":"function","dur":250107,"name":"void __cdecl ETOD::WindowsWindow::Init(const struct ETOD::WindowProps &)","ph":"X","pid":0,"tid":434243838,"ts":20602178784},{"cat":"function","dur":250180,"name":"__cdecl ETOD::WindowsWindow::WindowsWindow(const struct ETOD::WindowProps &)","ph":"X","pid":0,"tid":434243838,"ts":20602178784},{"cat":"function","dur":28,"name":"void __cdecl ETOD::OpenGLRendererAPI::Init(void)","ph":"X","pid":0,"tid":434243838,"ts":20602429014},{"cat":"function","dur":11,"name":"__cdecl ETOD::OpenGLVertexArray::OpenGLVertexArray(void)","ph":"X","pid":0,"tid":434243838,"ts":20602429128},{"cat":"function","dur":75,"name":"__cdecl ETOD::OpenGLVertexBuffer::OpenGLVertexBuffer(unsigned int)","ph":"X","pid":0,"tid":434243838,"ts":20602429240},{"cat":"function","dur":0,"name":"void __cdecl ETOD::OpenGLVertexBuffer::Bind(void) const","ph":"X","pid":0,"tid":434243838,"ts":20602429381},{"cat":"function","dur":49,"name":"void __cdecl ETOD::OpenGLVertexArray::AddVertexBuffer(const class std::shared_ptr<class ETOD::VertexBuffer> &)","ph":"X","pid":0,"tid":434243838,"ts":20602429378},{"cat":"function","dur":741,"name":"__cdecl ETOD::OpenGLIndexBuffer::OpenGLIndexBuffer(unsigned int *,unsigned int)","ph":"X","pid":0,"tid":434243838,"ts":20602430228},{"cat":"function","dur":1,"name":"void __cdecl ETOD::OpenGLIndexBuffer::Bind(void) const","ph":"X","pid":0,"tid":434243838,"ts":20602431038},{"cat":"function","dur":34,"name":"void __cdecl ETOD::OpenGLVertexArray::SetIndexBuffer(const class std::shared_ptr<class ETOD::IndexBuffer> &)","ph":"X","pid":0,"tid":434243838,"ts":20602431037},{"cat":"function","dur":802,"name":"__cdecl ETOD::OpenGLTexture2D::OpenGLTexture2D(unsigned int,unsigned int)","ph":"X","pid":0,"tid":434243838,"ts":20602431162},{"cat":"function","dur":89,"name":"void __cdecl ETOD::OpenGLTexture2D::SetData(void *,unsigned int)","ph":"X","pid":0,"tid":434243838,"ts":20602432081},{"cat":"function","dur":159,"name":"class std::basic_string<char,struct std::char_traits<char>,class std::allocator<char> > __cdecl ETOD::OpenGLShader::ReadFile(const class std::basic_string<char,struct std::char_traits<char>,class std::allocator<char> > &)","ph":"X","pid":0,"tid":434243838,"ts":20602432227},{"cat":"function","dur":43,"name":"class std::unordered_map<unsigned int,class std::basic_string<char,struct std::char_traits<char>,class std::allocator<char> >,struct std::hash<unsigned int>,struct std::equal_to<unsigned int>,class std::allocator<struct std::pair<unsigned int const ,class std::basic_string<char,struct std::char_traits<char>,class std::allocator<char> > > > > __cdecl ETOD::OpenGLShader::PreProcess(const class std::basic_string<char,struct std::char_traits<char>,class std::allocator<char> > &)","ph":"X","pid":0,"tid":434243838,"ts":20602432424},{"cat":"function","dur":17677,"name":"void __cdecl ETOD::OpenGLShader::Compile(const class std::unordered_map<unsigned int,class std::basic_string<char,struct std::char_traits<char>,class std::allocator<char> >,struct std::hash<unsigned int>,struct std::equal_to<unsigned int>,class std::allocator<struct std::pair<unsigned int const ,class std::basic_string<char,struct std::char_traits<char>,class std::allocator<char> > > > > &)","ph":"X","pid":0,"tid":434243838,"ts":20602432507},{"cat":"function","dur":18098,"name":"__cdecl ETOD::OpenGLShader::OpenGLShader(const class std::basic_string<char,struct std::char_traits<char>,class std::allocator<char> > &)","ph":"X","pid":0,"tid":434243838,"ts":20602432225},{"cat":"function","dur":33,"name":"void __cdecl ETOD::OpenGLShader::Bind(void) const","ph":"X","pid":0,"tid":434243838,"ts":20602450387},{"cat":"function","dur":21474,"name":"void __cdecl ETOD::Renderer2D::Init(void)","ph":"X","pid":0,"tid":434243838,"ts":20602429102},{"cat":"function","dur":21601,"name":"void __cdecl ETOD::Renderer::Init(void)","ph":"X","pid":0,"tid":434243838,"ts":20602429014},{"cat":"function","dur":228,"name":"void __cdecl ETOD::ImGuiLayer::OnAttach(void)","ph":"X","pid":0,"tid":434243838,"ts":20602450652},{"cat":"function","dur":270,"name":"void __cdecl ETOD::Application::PushOverlay(class ETOD::Layer *)","ph":"X","pid":0,"tid":434243838,"ts":20602450648},{"cat":"function","dur":272175,"name":"__cdecl ETOD::Application::Application(const class std::basic_string<char,struct std::char_traits<char>,class std::allocator<char> > &)","ph":"X","pid":0,"tid":434243838,"ts":20602178771},{"cat":"function","dur":8,"name":"__cdecl ETOD::OrthographicCamera::OrthographicCamera(float,float,float,float)","ph":"X","pid":0,"tid":434243838,"ts":20602450994},{"cat":"function","dur":244,"name":"stbi_load - OpenGLTexture2D::OpenGLTexture2D(const std::string&)","ph":"X","pid":0,"tid":434243838,"ts":20602451051},{"cat":"function","dur":5384,"name":"__cdecl ETOD::OpenGLTexture2D::OpenGLTexture2D(const class std::basic_string<char,struct std::char_traits<char>,class std::allocator<char> > &)","ph":"X","pid":0,"tid":434243838,"ts":20602451047},{"cat":"function","dur":17129,"name":"void __cdecl ETOD::EditorLayer::OnAttach(void)","ph":"X","pid":0,"tid":434243838,"ts":20602451043},{"cat":"function","dur":17211,"name":"void __cdecl ETOD::Application::PushLayer(class ETOD::Layer *)","ph":"X","pid":0,"tid":434243838,"ts":20602451032}]}